nurphy/__init__.py
nurphy/bert/__init__.py
nurphy/bert/att_all_you_need.py
nurphy/bert/attention_test.py
nurphy/bert/bart_classification.py
nurphy/bert/bart_mask_filling.py
nurphy/bert/bart_nmt.py
nurphy/bert/bart_summarizer.py
nurphy/bert/bert_classification_model.py
nurphy/bert/bert_dataset.py
nurphy/bert/bert_predictor.py
nurphy/bert/bert_trainer.py
nurphy/bert/bert_util.py
nurphy/bert/gpt3.py
nurphy/bert/load_kobert_model.py
nurphy/bert/tokenization_hanbert.py
nurphy/bert/tokenization_kobert.py
nurphy/convAI/__init__.py
nurphy/convAI/bert_mini_chatbot.py
nurphy/convAI/chatbot_trainer.py
nurphy/convAI/chatbot_utils.py
nurphy/convAI/example_entry.py
nurphy/convAI/export_question_embeddings.py
nurphy/convAI/gpt2_chitchat_trainer.py
nurphy/convAI/interact.py
nurphy/convAI/test_special_tokens.py
nurphy/data_utils/__init__.py
nurphy/data_utils/ner_dataset.py
nurphy/data_utils/pad_sequence.py
nurphy/data_utils/relation_dataset.py
nurphy/data_utils/translation_dataset.py
nurphy/data_utils/util.py
nurphy/data_utils/utils.py
nurphy/data_utils/vocab_tokenizer.py
nurphy/examples/__init__.py
nurphy/examples/app.py
nurphy/examples/bart_summarization_test.py
nurphy/examples/bert_en_word_embeddings.py
nurphy/examples/bert_ko_word_embeddings.py
nurphy/examples/bert_sentiment_predictor.py
nurphy/examples/bert_sentiment_trainer.py
nurphy/examples/bpe.py
nurphy/examples/chitchat.py
nurphy/examples/clip_conversion.py
nurphy/examples/clip_zero_shot_prediction.py
nurphy/examples/convert_unicode.py
nurphy/examples/coqa_predictor.py
nurphy/examples/csp_extract.py
nurphy/examples/dialogpt_example.py
nurphy/examples/doc2vec_clustering.py
nurphy/examples/doc2vec_tester.py
nurphy/examples/doc2vec_trainer.py
nurphy/examples/elastic_search.py
nurphy/examples/elastic_search_embeddings.py
nurphy/examples/electra_test.py
nurphy/examples/es_embeddings_search.py
nurphy/examples/fasttext_tester.py
nurphy/examples/fasttext_trainer.py
nurphy/examples/glove_tester.py
nurphy/examples/gpt2_example1.py
nurphy-1.1.28.dist-info/LICENSE
nurphy-1.1.28.dist-info/METADATA
nurphy-1.1.28.dist-info/WHEEL
nurphy-1.1.28.dist-info/top_level.txt
nurphy-1.1.28.dist-info/RECORD
