Metadata-Version: 2.1
Name: nurphy
Version: 1.1.28
Summary: A deep learning based natural language understanding module
Home-page: https://github.com/MinSong2/nurphy
Author: Min Song
Author-email: min.song@onomaai.com
Classifier: Programming Language :: Python :: 3
Classifier: License :: OSI Approved :: MIT License
Classifier: Operating System :: OS Independent
Requires-Python: >=3.10
License-File: LICENSE
Requires-Dist: pandas
Requires-Dist: cython
Requires-Dist: seqeval
Requires-Dist: pytorch-crf
Requires-Dist: numpy
Requires-Dist: sklearn-crfsuite
Requires-Dist: gensim
Requires-Dist: konlpy
Requires-Dist: krwordrank
Requires-Dist: lxml
Requires-Dist: matplotlib
Requires-Dist: networkx
Requires-Dist: node2vec
Requires-Dist: bs4
Requires-Dist: pycrfsuite-spacing
Requires-Dist: scikit-learn
Requires-Dist: scipy
Requires-Dist: seaborn
Requires-Dist: soynlp
Requires-Dist: torch
Requires-Dist: tomotopy
Requires-Dist: pyLDAvis
Requires-Dist: wordcloud
Requires-Dist: nltk
Requires-Dist: newspaper3k
Requires-Dist: selenium
Requires-Dist: soylemma
Requires-Dist: bokeh
Requires-Dist: beautifulsoup4
Requires-Dist: benepar >=0.2.0
Requires-Dist: boto3
Requires-Dist: kobert-transformers
Requires-Dist: treform
Requires-Dist: openai
Requires-Dist: pytorch-ignite
Requires-Dist: fire
Requires-Dist: pytorch-lightning
Requires-Dist: streamlit
Requires-Dist: elasticsearch
Requires-Dist: sentence-transformers
Requires-Dist: st-card-component
